python_nbs/Instrument.py
python_nbs/Layer.py
python_nbs/NoteBlock.py
python_nbs/__init__.py
python_nbs/binary.py
python_nbs/nbs.py
Python_NBS-1.0.0.dist-info/LICENSE
Python_NBS-1.0.0.dist-info/METADATA
Python_NBS-1.0.0.dist-info/WHEEL
Python_NBS-1.0.0.dist-info/top_level.txt
Python_NBS-1.0.0.dist-info/RECORD
