Metadata-Version: 2.1
Name: Python-NBS
Version: 1.0.0
Summary: A python library for loading NBS files
Home-page: https://github.com/kemo14331/Python-NBS
Author: Kemo431
License: MIT
Platform: UNKNOWN
Classifier: Development Status :: 3 - Alpha
Classifier: Intended Audience :: Developers
Classifier: License :: OSI Approved :: MIT License
Classifier: Operating System :: OS Independent
Classifier: Programming Language :: Python :: 3
Classifier: Topic :: Games/Entertainment
Classifier: Topic :: Software Development :: Libraries :: Python Modules
Provides-Extra: develop
